{
	"__comment": "Unlocks the gravel from flint recipe.",
	"parent": "minecraft:recipes/root",
	"criteria": {
		"has_flint": {
			"trigger": "minecraft:inventory_changed",
			"conditions": {
				"items": [
					{
						"item": "minecraft:flint"
					}
				]
			}
		},
    "has_gravel": {
			"trigger": "minecraft:inventory_changed",
			"conditions": {
				"items": [
					{
						"item": "minecraft:gravel"
					}
				]
			}
		}
	},
	"requirements": [
		[
			"has_gravel",
			"has_flint"
		]
	],
	"rewards": {
		"recipes": [
			"3rd-block:gravel"
		]
	}
}
